mythic_translator_container/MythicBaseRPC.py
mythic_translator_container/MythicRPC.py
mythic_translator_container/__init__.py
mythic_translator_container/config.py
mythic_translator_container/mythic_service.py
mythic_translator_container-0.0.18.dist-info/METADATA
mythic_translator_container-0.0.18.dist-info/WHEEL
mythic_translator_container-0.0.18.dist-info/top_level.txt
mythic_translator_container-0.0.18.dist-info/RECORD
