Metadata-Version: 2.1
Name: mythic-translator-container
Version: 0.0.18
Summary: Functionality for Mythic C2 Translator Containers
Home-page: https://docs.mythic-c2.net/customizing/c2-related-development
Author: @its_a_feature_
Author-email: 
License: BSD3
Platform: UNKNOWN
Classifier: License :: Other/Proprietary License
Classifier: Programming Language :: Python :: 3
Classifier: Programming Language :: Python :: 3.8
Requires-Dist: pika
Requires-Dist: dynaconf
